setup.py
zawn_orm/__init__.py
zawn_orm/codec.py
zawn_orm/database.py
zawn_orm/exception.py
zawn_orm/field.py
zawn_orm/model.py
zawn_orm/state.py
zawn_orm/test.py
zawn_orm/tool.py
zawn_orm.egg-info/PKG-INFO
zawn_orm.egg-info/SOURCES.txt
zawn_orm.egg-info/dependency_links.txt
zawn_orm.egg-info/requires.txt
zawn_orm.egg-info/top_level.txt
zawn_orm/impl/__init__.py
zawn_orm/impl/mongodb.py
zawn_orm/impl/sqlite.py