Metadata-Version: 1.0
Name: zawn-orm
Version: 0.0.14
Summary: zawn's private utils.
Home-page: https://gitee.com/zawn/orm.git
Author: zawn
Author-email: zawn@qq.com
License: MIT Licence
Keywords: zawn,orm
Platform: any
